Workbook

Sheet Dashboard
A1: Halo Strategic — US HVAC LinkedIn Campaign
A2: Qualified-lead tracker. Source: halo-growth-hvac/BRIEF.md and CLAUDE_BROWSER_LINKEDIN_BRIEF.md. Fill in yellow cells only; everything else is a formula.
A4: Funnel totals
A5: Metric | B5: Value | C5: Notes
A6: Total spend ($) | B6: ='Campaign Summary'!B7 -> 0 | C6: Sum of both creatives, from Campaign Summary
A7: Total form submissions | B7: ='Campaign Summary'!G7 -> 0 | C7: From Campaign Summary
A8: Platform CPL ($) | B8: =IFERROR(B6/B7,0) -> 0 | C8: Total spend / total form submissions
A9: Qualified HVAC businesses | B9: =COUNTIF(Leads!G:G,"Y") -> 1 | C9: Leads sheet, Qualified = Y
A10: Qualified CPL ($) | B10: =IFERROR(B6/B9,0) -> 0 | C10: Total spend / qualified businesses
A11: Sales conversations | B11: =COUNTIF(Leads!H:H,"Y") -> 1 | C11: Leads sheet, Conversation held = Y
A12: Paid trials sold | B12: =COUNTIF(Leads!I:I,"Y") -> 0 | C12: Leads sheet, Trial purchased = Y
A13: Repeat purchases | B13: =COUNTIF(Leads!J:J,"Y") -> 0 | C13: Leads sheet, Repeat purchase = Y
A14: Revenue ($) | B14: =SUM(Leads!K:K) -> 0 | C14: Sum of Leads sheet Revenue column
A15: Cost to acquire one paying HVAC customer ($) | B15: =IFERROR(B6/B10,0) -> 0 | C15: Total spend / paid trials sold — the PRIMARY KPI per BRIEF.md §11, not raw cost-per-lead
A17: Remember: the goal is proving one real HVAC company will pay for 5 opportunities and Halo can deliver them, not maximising form-fill volume (BRIEF.md §1).

Sheet Campaign Summary
A1: Campaign Summary — enter from LinkedIn Campaign Manager
A2: Yellow cells = enter by hand from Campaign Manager. One row per creative; Total row sums both. Test budget: $300 total (halo-growth-hvac/CLAUDE_BROWSER_LINKEDIN_BRIEF.md).
A4: Concept | B4: Spend ($) | C4: Impressions | D4: Clicks | E4: CTR | F4: Form opens | G4: Form submissions | H4: Platform CPL ($) | I4: Qualified businesses | J4: Qualified CPL ($)
A5: A — Stop Splitting Leads With 3 Other Contractors | B5: 0 | C5: 0 | D5: 0 | E5: =IFERROR(D5/C5,0) -> 0 | F5: 0 | G5: 0 | H5: =IFERROR(B5/G5,0) -> 0 | I5: =COUNTIFS(Leads!$F:$F,"A",Leads!$G:$G,"Y") -> 1 | J5: =IFERROR(B5/I5,0) -> 0
A6: C — $150 Per Qualified Opportunity, Not Per Dead Number | B6: 0 | C6: 0 | D6: 0 | E6: =IFERROR(D6/C6,0) -> 0 | F6: 0 | G6: 0 | H6: =IFERROR(B6/G6,0) -> 0 | I6: =COUNTIFS(Leads!$F:$F,"C",Leads!$G:$G,"Y") -> 0 | J6: =IFERROR(B6/I6,0) -> 0
A7: Total | B7: =SUM(B5:B6) -> 0 | C7: =SUM(C5:C6) -> 0 | D7: =SUM(D5:D6) -> 0 | E7: =IFERROR(D7/C7,0) -> 0 | F7: =SUM(F5:F6) -> 0 | G7: =SUM(G5:G6) -> 0 | H7: =IFERROR(B7/G7,0) -> 0 | I7: =SUM(I5:I6) -> 1 | J7: =IFERROR(B7/I7,0) -> 0

Sheet Leads
A1: Leads — one row per HVAC business submission
A2: Populated automatically by two Make.com scenarios (one per ad, see Make.com Setup tab), or paste in manually from a LinkedIn Campaign Manager CSV export meanwhile.
A4: Date | B4: Company | C4: Contact name | D4: Email | E4: Phone | F4: Concept (A/C) | G4: Qualified? (Y/N) | H4: Sales conversation held? (Y/N) | I4: Trial purchased? (Y/N) | J4: Repeat purchase? (Y/N) | K4: Revenue ($) | L4: Notes
A5: 2026-09-15 | B5: Coastal Air HVAC LLC | C5: Mike Torres | D5: mike@coastalairhvac.com | E5: 555-0134 | F5: A | G5: Y | H5: Y | I5: N | J5: N | K5: 0 | L5: Example row — delete before real data. Real local HVAC contractor, 6 technicians, currently on Angi.

Sheet Make.com Setup
A1: Connecting LinkedIn Lead Gen Forms to this sheet via Make.com
A2: Decided: two separate Lead Gen Forms (one per ad), each with its own Make scenario, plus an email notification to Fabien on every new lead. I have no LinkedIn, Make.com, or Gmail access in this session, so this hasn't been built or tested; verify against Make's actual current UI as you go.
A4: 0. In Campaign Manager, build two Lead Gen Forms with identical content (same fields, headline, supporting copy, confirmation message from CLAUDE_BROWSER_LINKEDIN_BRIEF.md), one attached to Ad 1 (Concept A) and one to Ad 2 (Concept C). Needed so each Make scenario can watch its own form and know which concept it belongs to.
A5: 1. Import this file into Google Sheets first (File > Import > Upload, replace spreadsheet), Make writes to a live Google Sheet, not a local .xlsx.
A6: 2. Build Scenario 1 (Concept A): trigger module 'LinkedIn Lead Gen Ads' -> 'Watch Leads', connect the LinkedIn Ads account, select the Concept A form specifically.
A7: 3. Action module 1: 'Google Sheets' -> 'Add a Row', target this spreadsheet's 'Leads' tab. Map Date -> now(), Company/Contact name/Email/Phone -> the matching form fields, and set the 'Concept (A/C)' column to a static value: A.
A8: 4. Action module 2 (same scenario, runs right after Add a Row): 'Gmail' (or 'Email' module) -> 'Send an Email', to fabien@halostrategic.com. Subject: 'New HVAC lead (Concept A): {{Company}}'. Body: include Company, Contact name, Email, Phone, and a link to this sheet's Leads tab, so Fabien can act within the 15-minute SLA without opening the sheet first.
A9: 5. Build Scenario 2 (Concept C): identical to Scenario 1, but watching the Concept C form, 'Concept (A/C)' set to a static value: C, and the email subject reading 'New HVAC lead (Concept C): {{Company}}'.
A10: 6. Qualified, Sales conversation held, Trial purchased, Repeat purchase, and Revenue are not in LinkedIn's form, leave those blank in both scenarios for manual entry after each lead comes in.
A11: 7. Run each scenario once manually with a test submission before scheduling, confirm both the sheet row and the email actually arrive correctly.
A12: 8. Turn both scenarios on. From this point, every new form submission on either ad should append a correctly-attributed row AND send Fabien an email, automatically.
A14: Email volume note: at a genuinely low lead volume (this is a $300 test), one email per lead is fine. If volume grows later, worth revisiting whether Fabien wants a per-lead email forever or a digest, a decision for that point, not this one.
